gdbrpc/__init__.py
gdbrpc/__main__.py
gdbrpc/_version.py
gdbrpc/cli.py
gdbrpc/client.py
gdbrpc/commands.py
gdbrpc/server.py
gdbrpc/utils.py
gdbrpc/examples/getheaps.py
gdbrpc/examples/memleak.py
gdbrpc/tests/stresstest.py
gdbrpc-0.5.0.dist-info/licenses/LICENSE
gdbrpc-0.5.0.dist-info/METADATA
gdbrpc-0.5.0.dist-info/WHEEL
gdbrpc-0.5.0.dist-info/top_level.txt
gdbrpc-0.5.0.dist-info/RECORD
