Metadata-Version: 2.4
Name: gdbrpc
Version: 0.5.0
Summary: A Python RPC framework for controlling GDB remotely - enables programmatic debugging automation, remote command execution, and interactive CLI for any GDB-compatible debugger
Maintainer-email: suoyuan <s5n666@outlook.com>, Neo Xu <neo.xu1990@gmail.com>
License-Expression: Apache-2.0
Project-URL: Homepage, https://github.com/suoyuanG/gdbrpc
Project-URL: Issues, https://github.com/suoyuanG/gdbrpc/issues
Keywords: gdb,remote,rpc,debugger,debugging,automation,NuttX,embedded
Classifier: Programming Language :: Python :: 3
Classifier: Programming Language :: Python :: 3.10
Requires-Python: >=3.10
License-File: LICENSE
Requires-Dist: cloudpickle>=0.0.0
Dynamic: license-file
